setup.py
LibrosLibros02.egg-info/PKG-INFO
LibrosLibros02.egg-info/SOURCES.txt
LibrosLibros02.egg-info/dependency_links.txt
LibrosLibros02.egg-info/not-zip-safe
LibrosLibros02.egg-info/top_level.txt
OneSignal/OSConnection.py
OneSignal/OSHeader.py
OneSignal/OSPayload.py
OneSignal/OSResponse.py
OneSignal/__init__.py