Metadata-Version: 1.0
Name: LibrosLibros02
Version: 0.1
Summary: Integracion OneSignal
Home-page: http://github.com/storborg/funniest
Author: Isodinamia
Author-email: info@isodinamia.com
License: MIT
Platform: UNKNOWN
